ddate/__init__.py
ddate/base.py
ddate/dcal.py
ddate-0.1.2.dist-info/LICENSE
ddate-0.1.2.dist-info/METADATA
ddate-0.1.2.dist-info/WHEEL
ddate-0.1.2.dist-info/entry_points.txt
ddate-0.1.2.dist-info/top_level.txt
ddate-0.1.2.dist-info/RECORD
