Metadata-Version: 2.1
Name: ddate
Version: 0.1.2
Summary: Discordian date and calendar
Home-page: http://a-tal.github.io/ddate
Author: Adam Talsma
Author-email: adam@talsma.ca
License: BSD
Download-URL: https://github.com/a-tal/ddate
Platform: UNKNOWN
Classifier: Development Status :: 5 - Production/Stable
Classifier: Environment :: Console
Classifier: Intended Audience :: System Administrators
Classifier: License :: OSI Approved :: BSD License
Classifier: Operating System :: POSIX :: Linux
Classifier: Programming Language :: Python
Requires-Dist: dateandtime
